chibi_apache/__init__.py
chibi_apache/apache.py
chibi_apache-0.0.2.dist-info/AUTHORS.rst
chibi_apache-0.0.2.dist-info/LICENSE
chibi_apache-0.0.2.dist-info/METADATA
chibi_apache-0.0.2.dist-info/WHEEL
chibi_apache-0.0.2.dist-info/top_level.txt
chibi_apache-0.0.2.dist-info/RECORD
