Metadata-Version: 2.1
Name: chibi-apache
Version: 0.0.2
Summary: libreria para leer y escribir los archivos de configuracion de apache
Home-page: https://github.com/dem4ply/chibi_apache
Author: dem4ply
Author-email: dem4ply@gmail.com
License: WTFPL
Keywords: chibi_apache
Classifier: Development Status :: 2 - Pre-Alpha
Classifier: Intended Audience :: Developers
Classifier: License :: Public Domain
Classifier: Natural Language :: English
Classifier: Programming Language :: Python :: 3.7
Classifier: Programming Language :: Python :: 3.8
License-File: LICENSE
License-File: AUTHORS.rst
Requires-Dist: chibi (>=0.11.7)
